nlboard/__init__.py
nlboard/main.py
nlboard/prompts.py
nlboard-2025.12.21124952.dist-info/METADATA
nlboard-2025.12.21124952.dist-info/WHEEL
nlboard-2025.12.21124952.dist-info/top_level.txt
nlboard-2025.12.21124952.dist-info/RECORD
