Metadata-Version: 2.4
Name: nlboard
Version: 2025.12.21124952
Summary: A new package that transforms unstructured user input about project management needs into a structured Trello-like board setup. Users describe their tasks, workflows, and preferences in plain text, an
Author-email: nlboard <hi@eugene.plus>
License: MIT
Project-URL: Homepage, https://github.com/chigwell/nlboard
Requires-Python: >=3.9
Requires-Dist: langchain-llm7>=0.0.0
Requires-Dist: llmatch-messages>=0.0.0
Requires-Dist: langchain-core>=0.3.0
